[
  {
    "name": "forgot-password",
    "path": "/forgot-password",
    "component": "C:\\\\Users\\\\rodri\\\\Desktop\\\\Comets\\\\frontend\\\\comets-js\\\\pages\\\\forgot-password.vue",
    "chunkName": "pages/forgot-password"
  },
  {
    "name": "login",
    "path": "/login",
    "component": "C:\\\\Users\\\\rodri\\\\Desktop\\\\Comets\\\\frontend\\\\comets-js\\\\pages\\\\login.vue",
    "chunkName": "pages/login"
  },
  {
    "name": "profile",
    "path": "/profile",
    "component": "C:\\\\Users\\\\rodri\\\\Desktop\\\\Comets\\\\frontend\\\\comets-js\\\\pages\\\\profile.vue",
    "chunkName": "pages/profile"
  },
  {
    "name": "register",
    "path": "/register",
    "component": "C:\\\\Users\\\\rodri\\\\Desktop\\\\Comets\\\\frontend\\\\comets-js\\\\pages\\\\register.vue",
    "chunkName": "pages/register"
  },
  {
    "name": "reset-password",
    "path": "/reset-password",
    "component": "C:\\\\Users\\\\rodri\\\\Desktop\\\\Comets\\\\frontend\\\\comets-js\\\\pages\\\\reset-password.vue",
    "chunkName": "pages/reset-password"
  },
  {
    "name": "products-id",
    "path": "/products/:id",
    "component": "C:\\\\Users\\\\rodri\\\\Desktop\\\\Comets\\\\frontend\\\\comets-js\\\\pages\\\\products\\\\_id\\\\index.vue",
    "chunkName": "pages/products/_id/index"
  },
  {
    "name": "index",
    "path": "/",
    "component": "C:\\\\Users\\\\rodri\\\\Desktop\\\\Comets\\\\frontend\\\\comets-js\\\\pages\\\\index.vue",
    "chunkName": "pages/index"
  }
]
